skriba/__init__.py
skriba/console.py
skriba/logger.py
skriba/plugins/worker_logger.py
skriba-0.3.13.dist-info/METADATA
skriba-0.3.13.dist-info/WHEEL
skriba-0.3.13.dist-info/top_level.txt
skriba-0.3.13.dist-info/RECORD
