Metadata-Version: 2.1
Name: skriba
Version: 0.3.13
Summary: Messaging and logger module for astroVIPER, Dask based ecosystem.
Author-email: Joshua Hoskins <jhoskins@nrao.edu>
Project-URL: Homepage, https://odysseus.jetbrains.space/p/main/repositories/skriba
Requires-Python: <3.12,>=3.8
Requires-Dist: colorama
Requires-Dist: dask
Requires-Dist: distributed
Requires-Dist: pytest
Requires-Dist: pytest-cov
Requires-Dist: pytest-html
Requires-Dist: rich
Provides-Extra: docs
Requires-Dist: ipykernel ; extra == 'docs'
Requires-Dist: ipympl ; extra == 'docs'
Requires-Dist: ipython ; extra == 'docs'
Requires-Dist: nbsphinx ; extra == 'docs'
Requires-Dist: recommonmark ; extra == 'docs'
Requires-Dist: scanpydoc ; extra == 'docs'
Requires-Dist: sphinx-autoapi ; extra == 'docs'
Requires-Dist: sphinx-autosummary-accessors ; extra == 'docs'
Requires-Dist: sphinx-rtd-theme ; extra == 'docs'
Requires-Dist: twine ; extra == 'docs'
Requires-Dist: pandoc ; extra == 'docs'
